back_up/__init__.py
back_up/__main__.py
back_up-1.0.0.dist-info/METADATA
back_up-1.0.0.dist-info/WHEEL
back_up-1.0.0.dist-info/entry_points.txt
back_up-1.0.0.dist-info/top_level.txt
back_up-1.0.0.dist-info/RECORD
