Metadata-Version: 2.1
Name: back-up
Version: 1.0.0
Summary: Back up directories efficiently.
Home-page: https://github.com/Czaporka/back-up
Author: Czaporka
License: MIT
Keywords: backup
Platform: UNKNOWN
Classifier: Development Status :: 4 - Beta
Classifier: License :: OSI Approved :: MIT License
Classifier: Operating System :: OS Independent
Classifier: Programming Language :: Python :: 3
Classifier: Programming Language :: Python :: 3.7
Classifier: Topic :: System :: Archiving :: Backup
Requires-Python: >=3.7
Requires-Dist: PyYAML (==5.3.1)
